Metadata-Version: 2.1
Name: color-palette-at
Version: 0.1.6
Summary: Library that allows to get a color palette from an image.
Home-page: UNKNOWN
Author: Adam Tabaczyński
Author-email: adam.tabaczynski96@gmail.com
License: MIT
Keywords: color color_palette colors
Platform: UNKNOWN
Classifier: Programming Language :: Python :: 3.6
Classifier: Development Status :: 3 - Alpha
Classifier: Topic :: Utilities
Classifier: License :: OSI Approved :: MIT License
Requires-Python: >=3.6
License-File: LICENSE.txt
